{"nodes": [{"id": "psx_tracker_scheduler_py", "label": "scheduler.py", "file_type": "code", "source_file": "psx_tracker\\scheduler.py", "source_location": "L1"}, {"id": "scheduler_eod_job", "label": "_eod_job()", "file_type": "code", "source_file": "psx_tracker\\scheduler.py", "source_location": "L21"}, {"id": "scheduler_ticker_refresh_job", "label": "_ticker_refresh_job()", "file_type": "code", "source_file": "psx_tracker\\scheduler.py", "source_location": "L29"}, {"id": "scheduler_catch_up", "label": "_catch_up()", "file_type": "code", "source_file": "psx_tracker\\scheduler.py", "source_location": "L33"}, {"id": "scheduler_run", "label": "run()", "file_type": "code", "source_file": "psx_tracker\\scheduler.py", "source_location": "L53"}, {"id": "scheduler_rationale_1", "label": "Runs as a long-lived process.  Every weekday at EOD_FETCH_TIME (PKT) it fetches", "file_type": "rationale", "source_file": "psx_tracker\\scheduler.py", "source_location": "L1"}, {"id": "scheduler_rationale_34", "label": "If the process was offline, backfill missing trading days.", "file_type": "rationale", "source_file": "psx_tracker\\scheduler.py", "source_location": "L34"}], "edges": [{"source": "psx_tracker_scheduler_py", "target": "signal", "relation": "imports", "confidence": "EXTRACTED", "source_file": "psx_tracker\\scheduler.py", "source_location": "L8", "weight": 1.0}, {"source": "psx_tracker_scheduler_py", "target": "sys", "relation": "imports", "confidence": "EXTRACTED", "source_file": "psx_tracker\\scheduler.py", "source_location": "L9", "weight": 1.0}, {"source": "psx_tracker_scheduler_py", "target": "time", "relation": "imports", "confidence": "EXTRACTED", "source_file": "psx_tracker\\scheduler.py", "source_location": "L10", "weight": 1.0}, {"source": "psx_tracker_scheduler_py", "target": "datetime", "relation": "imports_from", "confidence": "EXTRACTED", "source_file": "psx_tracker\\scheduler.py", "source_location": "L11", "weight": 1.0}, {"source": "psx_tracker_scheduler_py", "target": "schedule", "relation": "imports", "confidence": "EXTRACTED", "source_file": "psx_tracker\\scheduler.py", "source_location": "L13", "weight": 1.0}, {"source": "psx_tracker_scheduler_py", "target": "config", "relation": "imports_from", "confidence": "EXTRACTED", "source_file": "psx_tracker\\scheduler.py", "source_location": "L15", "weight": 1.0}, {"source": "psx_tracker_scheduler_py", "target": "database", "relation": "imports_from", "confidence": "EXTRACTED", "source_file": "psx_tracker\\scheduler.py", "source_location": "L16", "weight": 1.0}, {"source": "psx_tracker_scheduler_py", "target": "fetcher", "relation": "imports_from", "confidence": "EXTRACTED", "source_file": "psx_tracker\\scheduler.py", "source_location": "L17", "weight": 1.0}, {"source": "psx_tracker_scheduler_py", "target": "config", "relation": "imports_from", "confidence": "EXTRACTED", "source_file": "psx_tracker\\scheduler.py", "source_location": "L18", "weight": 1.0}, {"source": "psx_tracker_scheduler_py", "target": "scheduler_eod_job", "relation": "contains", "confidence": "EXTRACTED", "source_file": "psx_tracker\\scheduler.py", "source_location": "L21", "weight": 1.0}, {"source": "psx_tracker_scheduler_py", "target": "scheduler_ticker_refresh_job", "relation": "contains", "confidence": "EXTRACTED", "source_file": "psx_tracker\\scheduler.py", "source_location": "L29", "weight": 1.0}, {"source": "psx_tracker_scheduler_py", "target": "scheduler_catch_up", "relation": "contains", "confidence": "EXTRACTED", "source_file": "psx_tracker\\scheduler.py", "source_location": "L33", "weight": 1.0}, {"source": "psx_tracker_scheduler_py", "target": "scheduler_run", "relation": "contains", "confidence": "EXTRACTED", "source_file": "psx_tracker\\scheduler.py", "source_location": "L53", "weight": 1.0}, {"source": "scheduler_run", "target": "scheduler_catch_up", "relation": "calls", "confidence": "EXTRACTED", "source_file": "psx_tracker\\scheduler.py", "source_location": "L56", "weight": 1.0}, {"source": "scheduler_rationale_1", "target": "psx_tracker_scheduler_py", "relation": "rationale_for", "confidence": "EXTRACTED", "source_file": "psx_tracker\\scheduler.py", "source_location": "L1", "weight": 1.0}, {"source": "scheduler_rationale_34", "target": "scheduler_catch_up", "relation": "rationale_for", "confidence": "EXTRACTED", "source_file": "psx_tracker\\scheduler.py", "source_location": "L34", "weight": 1.0}], "raw_calls": [{"caller_nid": "scheduler_eod_job", "callee": "today", "source_file": "psx_tracker\\scheduler.py", "source_location": "L22"}, {"caller_nid": "scheduler_eod_job", "callee": "weekday", "source_file": "psx_tracker\\scheduler.py", "source_location": "L23"}, {"caller_nid": "scheduler_eod_job", "callee": "print", "source_file": "psx_tracker\\scheduler.py", "source_location": "L24"}, {"caller_nid": "scheduler_eod_job", "callee": "fetch_day", "source_file": "psx_tracker\\scheduler.py", "source_location": "L26"}, {"caller_nid": "scheduler_ticker_refresh_job", "callee": "refresh_tickers", "source_file": "psx_tracker\\scheduler.py", "source_location": "L30"}, {"caller_nid": "scheduler_catch_up", "callee": "last_fetch_date", "source_file": "psx_tracker\\scheduler.py", "source_location": "L37"}, {"caller_nid": "scheduler_catch_up", "callee": "fromisoformat", "source_file": "psx_tracker\\scheduler.py", "source_location": "L43"}, {"caller_nid": "scheduler_catch_up", "callee": "timedelta", "source_file": "psx_tracker\\scheduler.py", "source_location": "L43"}, {"caller_nid": "scheduler_catch_up", "callee": "today", "source_file": "psx_tracker\\scheduler.py", "source_location": "L45"}, {"caller_nid": "scheduler_catch_up", "callee": "print", "source_file": "psx_tracker\\scheduler.py", "source_location": "L47"}, {"caller_nid": "scheduler_catch_up", "callee": "backfill", "source_file": "psx_tracker\\scheduler.py", "source_location": "L48"}, {"caller_nid": "scheduler_catch_up", "callee": "print", "source_file": "psx_tracker\\scheduler.py", "source_location": "L50"}, {"caller_nid": "scheduler_run", "callee": "init_db", "source_file": "psx_tracker\\scheduler.py", "source_location": "L54"}, {"caller_nid": "scheduler_run", "callee": "refresh_tickers", "source_file": "psx_tracker\\scheduler.py", "source_location": "L55"}, {"caller_nid": "scheduler_run", "callee": "do", "source_file": "psx_tracker\\scheduler.py", "source_location": "L59"}, {"caller_nid": "scheduler_run", "callee": "at", "source_file": "psx_tracker\\scheduler.py", "source_location": "L59"}, {"caller_nid": "scheduler_run", "callee": "every", "source_file": "psx_tracker\\scheduler.py", "source_location": "L59"}, {"caller_nid": "scheduler_run", "callee": "do", "source_file": "psx_tracker\\scheduler.py", "source_location": "L62"}, {"caller_nid": "scheduler_run", "callee": "at", "source_file": "psx_tracker\\scheduler.py", "source_location": "L62"}, {"caller_nid": "scheduler_run", "callee": "every", "source_file": "psx_tracker\\scheduler.py", "source_location": "L62"}, {"caller_nid": "scheduler_run", "callee": "print", "source_file": "psx_tracker\\scheduler.py", "source_location": "L64"}, {"caller_nid": "scheduler_run", "callee": "print", "source_file": "psx_tracker\\scheduler.py", "source_location": "L65"}, {"caller_nid": "scheduler_run", "callee": "signal", "source_file": "psx_tracker\\scheduler.py", "source_location": "L71"}, {"caller_nid": "scheduler_run", "callee": "signal", "source_file": "psx_tracker\\scheduler.py", "source_location": "L72"}, {"caller_nid": "scheduler_run", "callee": "run_pending", "source_file": "psx_tracker\\scheduler.py", "source_location": "L75"}, {"caller_nid": "scheduler_run", "callee": "sleep", "source_file": "psx_tracker\\scheduler.py", "source_location": "L76"}]}